monsql
tests
