Metadata-Version: 1.0
Name: monsql
Version: 0.2.0
Summary: MonSQL - Lightweight and use-friendly wrapper for multiple relational databases. Currently supporting MySQL, SQLite3, PostgreSQL
Home-page: https://github.com/firstprayer/monsql.git
Author: firstprayer
Author-email: zhangty10@gmail.com
License: UNKNOWN
Platform: UNKNOWN
